remoter/__init__.py
remoter/cli.py
remoter/remoter.py
remoter-0.1.1.dist-info/DESCRIPTION.rst
remoter-0.1.1.dist-info/METADATA
remoter-0.1.1.dist-info/RECORD
remoter-0.1.1.dist-info/WHEEL
remoter-0.1.1.dist-info/entry_points.txt
remoter-0.1.1.dist-info/metadata.json
remoter-0.1.1.dist-info/top_level.txt
