Metadata-Version: 2.0
Name: remoter
Version: 0.1.1
Summary: Python 3 compatible remote task runner
Home-page: https://github.com/levchik/remoter
Author: Lev Rubel
Author-email: rubel.lev@gmail.com
License: Apache Software License 2.0
Keywords: remoter
Platform: UNKNOWN
Classifier: Development Status :: 2 - Pre-Alpha
Classifier: Intended Audience :: Developers
Classifier: License :: OSI Approved :: Apache Software License
Classifier: Natural Language :: English
Classifier: Programming Language :: Python :: 3
Classifier: Programming Language :: Python :: 3.5
Requires-Dist: Click (>=6.0)
